synaptrix/__init__.py
synaptrix/util.py
synaptrix-1.2.2.dist-info/METADATA
synaptrix-1.2.2.dist-info/WHEEL
synaptrix-1.2.2.dist-info/licenses/LICENSE
synaptrix-1.2.2.dist-info/RECORD
