Metadata-Version: 2.4
Name: synaptrix
Version: 1.2.2
Summary: Library for live and offline denoising of multi-channel EEG data powered by auto-encoders, created by Synaptrix Labs Inc.
Project-URL: Homepage, https://github.com/Synaptrix-Labs/Synaptrix
Author-email: Eric Yao <eric@synaptrix-labs.com>, Mofei Wang <mofei@synaptrix-labs.com>, Rishi Arjun <rishi.arjun2011@gmail.com>, Mihir Bharti <mihir@synaptrix-labs.com>
License-Expression: Apache-2.0
License-File: LICENSE
Classifier: Operating System :: OS Independent
Classifier: Programming Language :: Python :: 3
Requires-Python: >=3.8
Requires-Dist: matplotlib~=3.7
Requires-Dist: numpy<=2.2.2,>=1.21
Requires-Dist: pandas~=2.2
Requires-Dist: pylsl~=1.17
Requires-Dist: requests~=2.3
Requires-Dist: scipy~=1.15
Requires-Dist: seaborn~=0.13
Requires-Dist: zstandard~=0.23.0
